xython/__init__.py
xython/comp/FunctionOperator.py
xython/comp/Functools.py
xython/comp/__init__.py
xython/comp/_meta.py
xython/comp/fn.py
xython_for_python-0.0.1.dist-info/DESCRIPTION.rst
xython_for_python-0.0.1.dist-info/METADATA
xython_for_python-0.0.1.dist-info/RECORD
xython_for_python-0.0.1.dist-info/WHEEL
xython_for_python-0.0.1.dist-info/metadata.json
xython_for_python-0.0.1.dist-info/top_level.txt
