Metadata-Version: 2.0
Name: xython-for-python
Version: 0.0.1
Summary: python functional utilities
Home-page: https://github.com/Xython/xython
Author: thautwarm
Author-email: twshere@outlook.com
License: MIT
Keywords: functional,function composition,readability
Platform: any
Classifier: Programming Language :: Python :: 2.7
Classifier: Programming Language :: Python :: 3.4
Classifier: Programming Language :: Python :: 3.5
Classifier: Programming Language :: Python :: 3.6
Classifier: Programming Language :: Python :: 3.7
Classifier: Programming Language :: Python :: Implementation :: CPython
